examples/__init__.py
examples/example.py
metrics_migration-0.1.2.dist-info/DESCRIPTION.rst
metrics_migration-0.1.2.dist-info/METADATA
metrics_migration-0.1.2.dist-info/RECORD
metrics_migration-0.1.2.dist-info/WHEEL
metrics_migration-0.1.2.dist-info/metadata.json
metrics_migration-0.1.2.dist-info/top_level.txt
migration/__init__.py
migration/migration.py
migration/schema_func.py
tests/__init__.py
tests/test_migration.py
