Metadata-Version: 2.0
Name: metrics-migration
Version: 0.1.2
Summary: a simple tool to help you migrate graphite metrics
Home-page: https://github.com/yunstanford/metrics-migration
Author: Yun Xu
Author-email: yunx@zillowgroup.com
License: UNKNOWN
Platform: UNKNOWN
Classifier: Development Status :: 3 - Alpha
Classifier: Operating System :: MacOS
Classifier: Operating System :: POSIX :: Linux
Classifier: Topic :: System :: Software Distribution
Classifier: License :: OSI Approved :: MIT License
Classifier: Programming Language :: Python
Classifier: Programming Language :: Python :: 3
Classifier: Programming Language :: Python :: 3.5
Requires-Dist: aiographite
